rucksack/__init__.py
rucksack/cli.py
rucksack/command_parser.py
rucksack/completer.py
rucksack/config_parser.py
rucksack/connection.py
rucksack/exceptions.py
rucksack-0.1.0.data/scripts/ruck
test/__init__.py
test/test_cli.py
test/test_command_parser.py
test/test_completer.py
test/test_config_parser.py
test/test_connection.py
rucksack-0.1.0.dist-info/LICENSE.md
rucksack-0.1.0.dist-info/METADATA
rucksack-0.1.0.dist-info/WHEEL
rucksack-0.1.0.dist-info/top_level.txt
rucksack-0.1.0.dist-info/RECORD
