Metadata-Version: 2.1
Name: rucksack
Version: 0.1.0
Summary: A place to store your useful one liners
Home-page: https://github.com/acritelli/rucksack
Author: Anthony Critelli
Author-email: critellia@gmail.com
License: UNKNOWN
Project-URL: Bug Tracker, https://github.com/acritelli/rucksack/issues
Platform: UNKNOWN
Classifier: Programming Language :: Python :: 3.8
Classifier: License :: OSI Approved :: MIT License
Classifier: Operating System :: POSIX :: Linux
Classifier: Environment :: Console
Classifier: Intended Audience :: Developers
Classifier: Intended Audience :: Information Technology
Classifier: Intended Audience :: System Administrators
Classifier: Topic :: Terminals
Requires-Python: >=3.8
License-File: LICENSE.md
Requires-Dist: prompt-toolkit (<4.0.0,>=3.0.23)
Requires-Dist: fabric (<3.0.0,>=2.6.0)
Requires-Dist: PyYAML (<7.0.0,>=6.0)
Requires-Dist: jinja2 (<4.0.0,>=3.0.3)
